{
  "_class": "symbolInstance",
  "booleanOperation": -1,
  "clippingMaskMode": 0,
  "do_objectID": "A1D91C1F-A9A3-417D-A4B6-325575511CAB",
  "exportOptions": {
    "_class": "exportOptions",
    "do_objectID": "E4933B56-D042-4142-A25C-CA9CFA1304DF",
    "exportFormats": [
    ],
    "includedLayerIds": [
    ],
    "layerOptions": 0,
    "shouldTrim": false
  },
  "frame": {
    "_class": "rect",
    "constrainProportions": false,
    "do_objectID": "2FA9BCA2-54F4-431B-AEB4-4FA70F668C05",
    "height": 100,
    "width": 100,
    "x": 1100,
    "y": 700
  },
  "hasClippingMask": false,
  "horizontalSpacing": 0,
  "isFixedToViewport": false,
  "isFlippedHorizontal": false,
  "isFlippedVertical": false,
  "isLocked": false,
  "isVisible": true,
  "layerListExpandedType": 0,
  "name": "color / 10 blue-indigo / 0600",
  "nameIsFixed": false,
  "overrideValues": [
  ],
  "resizingConstraint": 63,
  "resizingType": 0,
  "rotation": 0,
  "scale": 1,
  "shouldBreakMaskChain": false,
  "style": {
    "_class": "style",
    "do_objectID": "C3BFC407-7786-47D7-8760-4DDE6CDB0B5D",
    "endMarkerType": 0,
    "miterLimit": 10,
    "startMarkerType": 0,
    "windingRule": 1
  },
  "symbolID": "661B0E4B-82D3-45BA-BD51-59F96F1C1CB2",
  "verticalSpacing": 0
}