{
  "_class": "symbolInstance",
  "booleanOperation": -1,
  "clippingMaskMode": 0,
  "do_objectID": "E3CEFF50-BBAD-44FD-86AF-3DEBE31F71F1",
  "exportOptions": {
    "_class": "exportOptions",
    "do_objectID": "DE3C9F03-B9DA-4E8E-B4A6-5AA116B82E0F",
    "exportFormats": [
    ],
    "includedLayerIds": [
    ],
    "layerOptions": 0,
    "shouldTrim": false
  },
  "frame": {
    "_class": "rect",
    "constrainProportions": false,
    "do_objectID": "A7BE2356-94AC-4EB5-B86F-7631FA5F56CA",
    "height": 100,
    "width": 100,
    "x": 1300,
    "y": 1000
  },
  "hasClippingMask": false,
  "horizontalSpacing": 0,
  "isFixedToViewport": false,
  "isFlippedHorizontal": false,
  "isFlippedVertical": false,
  "isLocked": false,
  "isVisible": true,
  "layerListExpandedType": 0,
  "name": "color / 12 indigo-violet / 0900",
  "nameIsFixed": false,
  "overrideValues": [
  ],
  "resizingConstraint": 63,
  "resizingType": 0,
  "rotation": 0,
  "scale": 1,
  "shouldBreakMaskChain": false,
  "style": {
    "_class": "style",
    "do_objectID": "E2F07E50-D4ED-40B4-808A-BFB29985F146",
    "endMarkerType": 0,
    "miterLimit": 10,
    "startMarkerType": 0,
    "windingRule": 1
  },
  "symbolID": "3F0E0843-D573-4609-ADF5-4517A80C86B3",
  "verticalSpacing": 0
}