{
  "_class": "symbolInstance",
  "booleanOperation": -1,
  "clippingMaskMode": 0,
  "do_objectID": "020D0ABF-E49D-4482-91B1-78E5DCAACDF7",
  "exportOptions": {
    "_class": "exportOptions",
    "do_objectID": "90E43F6F-BA9A-4603-BDB7-6E7089F43F8E",
    "exportFormats": [
    ],
    "includedLayerIds": [
    ],
    "layerOptions": 0,
    "shouldTrim": false
  },
  "frame": {
    "_class": "rect",
    "constrainProportions": false,
    "do_objectID": "F398218C-A132-4D75-AD6B-409A25851C4F",
    "height": 100,
    "width": 100,
    "x": 0,
    "y": 0
  },
  "hasClippingMask": false,
  "horizontalSpacing": 0,
  "isFixedToViewport": false,
  "isFlippedHorizontal": false,
  "isFlippedVertical": false,
  "isLocked": false,
  "isVisible": true,
  "layerListExpandedType": 0,
  "name": "color / 00 gray / 0000",
  "nameIsFixed": false,
  "overrideValues": [
  ],
  "resizingConstraint": 63,
  "resizingType": 0,
  "rotation": 0,
  "scale": 1,
  "shouldBreakMaskChain": false,
  "style": {
    "_class": "style",
    "contextSettings": {
      "_class": "graphicsContextSettings",
      "blendMode": 0,
      "do_objectID": "DE0C837D-A294-4EEF-9375-CBE36D560C6C",
      "opacity": 0.4
    },
    "do_objectID": "CDECDF90-C6E2-419C-9848-DC086625CB70",
    "endMarkerType": 0,
    "miterLimit": 10,
    "startMarkerType": 0,
    "windingRule": 1
  },
  "symbolID": "ACF5E784-E1B4-4692-B73C-AE0967593C0C",
  "verticalSpacing": 0
}