{
  "_class": "symbolInstance",
  "booleanOperation": -1,
  "clippingMaskMode": 0,
  "do_objectID": "5C3DB33E-3789-40C8-938C-E386414FF53E",
  "exportOptions": {
    "_class": "exportOptions",
    "do_objectID": "D80EF7F2-1E60-4405-9080-E53C5B2A9749",
    "exportFormats": [
    ],
    "includedLayerIds": [
    ],
    "layerOptions": 0,
    "shouldTrim": false
  },
  "frame": {
    "_class": "rect",
    "constrainProportions": false,
    "do_objectID": "80B98DB2-DE0F-4B0F-AF9A-0D339702005E",
    "height": 100,
    "width": 100,
    "x": 0,
    "y": 0
  },
  "hasClippingMask": false,
  "horizontalSpacing": 0,
  "isFixedToViewport": false,
  "isFlippedHorizontal": false,
  "isFlippedVertical": false,
  "isLocked": false,
  "isVisible": true,
  "layerListExpandedType": 0,
  "name": "color / 99 scalers / shade / 0800",
  "nameIsFixed": false,
  "overrideValues": [
  ],
  "resizingConstraint": 63,
  "resizingType": 0,
  "rotation": 0,
  "scale": 1,
  "shouldBreakMaskChain": false,
  "style": {
    "_class": "style",
    "do_objectID": "28FC5DCE-2BC2-44CB-84CF-A4E53DC4632A",
    "endMarkerType": 0,
    "miterLimit": 10,
    "startMarkerType": 0,
    "windingRule": 1
  },
  "symbolID": "0AA231D6-7C49-4B1C-9A82-B1AE8B173712",
  "verticalSpacing": 0
}